[
  {
    "char": "あ",
    "romaji": "a",
    "group": "a",
    "category": "main"
  },
  {
    "char": "い",
    "romaji": "i",
    "group": "a",
    "category": "main"
  },
  {
    "char": "う",
    "romaji": "u",
    "group": "a",
    "category": "main"
  },
  {
    "char": "え",
    "romaji": "e",
    "group": "a",
    "category": "main"
  },
  {
    "char": "お",
    "romaji": "o",
    "group": "a",
    "category": "main"
  },
  {
    "char": "か",
    "romaji": "ka",
    "group": "k",
    "category": "main"
  },
  {
    "char": "き",
    "romaji": "ki",
    "group": "k",
    "category": "main"
  },
  {
    "char": "く",
    "romaji": "ku",
    "group": "k",
    "category": "main"
  },
  {
    "char": "け",
    "romaji": "ke",
    "group": "k",
    "category": "main"
  },
  {
    "char": "こ",
    "romaji": "ko",
    "group": "k",
    "category": "main"
  },
  {
    "char": "さ",
    "romaji": "sa",
    "group": "s",
    "category": "main"
  },
  {
    "char": "し",
    "romaji": "shi",
    "group": "s",
    "category": "main"
  },
  {
    "char": "す",
    "romaji": "su",
    "group": "s",
    "category": "main"
  },
  {
    "char": "せ",
    "romaji": "se",
    "group": "s",
    "category": "main"
  },
  {
    "char": "そ",
    "romaji": "so",
    "group": "s",
    "category": "main"
  },
  {
    "char": "た",
    "romaji": "ta",
    "group": "t",
    "category": "main"
  },
  {
    "char": "ち",
    "romaji": "chi",
    "group": "t",
    "category": "main"
  },
  {
    "char": "つ",
    "romaji": "tsu",
    "group": "t",
    "category": "main"
  },
  {
    "char": "て",
    "romaji": "te",
    "group": "t",
    "category": "main"
  },
  {
    "char": "と",
    "romaji": "to",
    "group": "t",
    "category": "main"
  },
  {
    "char": "な",
    "romaji": "na",
    "group": "n",
    "category": "main"
  },
  {
    "char": "に",
    "romaji": "ni",
    "group": "n",
    "category": "main"
  },
  {
    "char": "ぬ",
    "romaji": "nu",
    "group": "n",
    "category": "main"
  },
  {
    "char": "ね",
    "romaji": "ne",
    "group": "n",
    "category": "main"
  },
  {
    "char": "の",
    "romaji": "no",
    "group": "n",
    "category": "main"
  },
  {
    "char": "は",
    "romaji": "ha",
    "group": "h",
    "category": "main"
  },
  {
    "char": "ひ",
    "romaji": "hi",
    "group": "h",
    "category": "main"
  },
  {
    "char": "ふ",
    "romaji": "fu",
    "group": "h",
    "category": "main"
  },
  {
    "char": "へ",
    "romaji": "he",
    "group": "h",
    "category": "main"
  },
  {
    "char": "ほ",
    "romaji": "ho",
    "group": "h",
    "category": "main"
  },
  {
    "char": "ま",
    "romaji": "ma",
    "group": "m",
    "category": "main"
  },
  {
    "char": "み",
    "romaji": "mi",
    "group": "m",
    "category": "main"
  },
  {
    "char": "む",
    "romaji": "mu",
    "group": "m",
    "category": "main"
  },
  {
    "char": "め",
    "romaji": "me",
    "group": "m",
    "category": "main"
  },
  {
    "char": "も",
    "romaji": "mo",
    "group": "m",
    "category": "main"
  },
  {
    "char": "や",
    "romaji": "ya",
    "group": "y",
    "category": "main"
  },
  {
    "char": "ゆ",
    "romaji": "yu",
    "group": "y",
    "category": "main"
  },
  {
    "char": "よ",
    "romaji": "yo",
    "group": "y",
    "category": "main"
  },
  {
    "char": "ら",
    "romaji": "ra",
    "group": "r",
    "category": "main"
  },
  {
    "char": "り",
    "romaji": "ri",
    "group": "r",
    "category": "main"
  },
  {
    "char": "る",
    "romaji": "ru",
    "group": "r",
    "category": "main"
  },
  {
    "char": "れ",
    "romaji": "re",
    "group": "r",
    "category": "main"
  },
  {
    "char": "ろ",
    "romaji": "ro",
    "group": "r",
    "category": "main"
  },
  {
    "char": "わ",
    "romaji": "wa",
    "group": "w",
    "category": "main"
  },
  {
    "char": "を",
    "romaji": "wo",
    "group": "w",
    "category": "main"
  },
  {
    "char": "ん",
    "romaji": "n",
    "group": "w",
    "category": "main"
  },
  {
    "char": "が",
    "romaji": "ga",
    "group": "g",
    "category": "dakuten"
  },
  {
    "char": "ぎ",
    "romaji": "gi",
    "group": "g",
    "category": "dakuten"
  },
  {
    "char": "ぐ",
    "romaji": "gu",
    "group": "g",
    "category": "dakuten"
  },
  {
    "char": "げ",
    "romaji": "ge",
    "group": "g",
    "category": "dakuten"
  },
  {
    "char": "ご",
    "romaji": "go",
    "group": "g",
    "category": "dakuten"
  },
  {
    "char": "ざ",
    "romaji": "za",
    "group": "z",
    "category": "dakuten"
  },
  {
    "char": "じ",
    "romaji": "ji",
    "group": "z",
    "category": "dakuten"
  },
  {
    "char": "ず",
    "romaji": "zu",
    "group": "z",
    "category": "dakuten"
  },
  {
    "char": "ぜ",
    "romaji": "ze",
    "group": "z",
    "category": "dakuten"
  },
  {
    "char": "ぞ",
    "romaji": "zo",
    "group": "z",
    "category": "dakuten"
  },
  {
    "char": "だ",
    "romaji": "da",
    "group": "d",
    "category": "dakuten"
  },
  {
    "char": "ぢ",
    "romaji": "ji",
    "group": "d",
    "category": "dakuten"
  },
  {
    "char": "づ",
    "romaji": "zu",
    "group": "d",
    "category": "dakuten"
  },
  {
    "char": "で",
    "romaji": "de",
    "group": "d",
    "category": "dakuten"
  },
  {
    "char": "ど",
    "romaji": "do",
    "group": "d",
    "category": "dakuten"
  },
  {
    "char": "ば",
    "romaji": "ba",
    "group": "b",
    "category": "dakuten"
  },
  {
    "char": "び",
    "romaji": "bi",
    "group": "b",
    "category": "dakuten"
  },
  {
    "char": "ぶ",
    "romaji": "bu",
    "group": "b",
    "category": "dakuten"
  },
  {
    "char": "べ",
    "romaji": "be",
    "group": "b",
    "category": "dakuten"
  },
  {
    "char": "ぼ",
    "romaji": "bo",
    "group": "b",
    "category": "dakuten"
  },
  {
    "char": "ぱ",
    "romaji": "pa",
    "group": "p",
    "category": "dakuten"
  },
  {
    "char": "ぴ",
    "romaji": "pi",
    "group": "p",
    "category": "dakuten"
  },
  {
    "char": "ぷ",
    "romaji": "pu",
    "group": "p",
    "category": "dakuten"
  },
  {
    "char": "ぺ",
    "romaji": "pe",
    "group": "p",
    "category": "dakuten"
  },
  {
    "char": "ぽ",
    "romaji": "po",
    "group": "p",
    "category": "dakuten"
  },
  {
    "char": "きゃ",
    "romaji": "kya",
    "group": "ky",
    "category": "combination"
  },
  {
    "char": "きゅ",
    "romaji": "kyu",
    "group": "ky",
    "category": "combination"
  },
  {
    "char": "きょ",
    "romaji": "kyo",
    "group": "ky",
    "category": "combination"
  },
  {
    "char": "しゃ",
    "romaji": "sha",
    "group": "sh",
    "category": "combination"
  },
  {
    "char": "しゅ",
    "romaji": "shu",
    "group": "sh",
    "category": "combination"
  },
  {
    "char": "しょ",
    "romaji": "sho",
    "group": "sh",
    "category": "combination"
  },
  {
    "char": "ちゃ",
    "romaji": "cha",
    "group": "ch",
    "category": "combination"
  },
  {
    "char": "ちゅ",
    "romaji": "chu",
    "group": "ch",
    "category": "combination"
  },
  {
    "char": "ちょ",
    "romaji": "cho",
    "group": "ch",
    "category": "combination"
  },
  {
    "char": "にゃ",
    "romaji": "nya",
    "group": "ny",
    "category": "combination"
  },
  {
    "char": "にゅ",
    "romaji": "nyu",
    "group": "ny",
    "category": "combination"
  },
  {
    "char": "にょ",
    "romaji": "nyo",
    "group": "ny",
    "category": "combination"
  },
  {
    "char": "ひゃ",
    "romaji": "hya",
    "group": "hy",
    "category": "combination"
  },
  {
    "char": "ひゅ",
    "romaji": "hyu",
    "group": "hy",
    "category": "combination"
  },
  {
    "char": "ひょ",
    "romaji": "hyo",
    "group": "hy",
    "category": "combination"
  },
  {
    "char": "みゃ",
    "romaji": "mya",
    "group": "my",
    "category": "combination"
  },
  {
    "char": "みゅ",
    "romaji": "myu",
    "group": "my",
    "category": "combination"
  },
  {
    "char": "みょ",
    "romaji": "myo",
    "group": "my",
    "category": "combination"
  },
  {
    "char": "りゃ",
    "romaji": "rya",
    "group": "ry",
    "category": "combination"
  },
  {
    "char": "りゅ",
    "romaji": "ryu",
    "group": "ry",
    "category": "combination"
  },
  {
    "char": "りょ",
    "romaji": "ryo",
    "group": "ry",
    "category": "combination"
  },
  {
    "char": "ぎゃ",
    "romaji": "gya",
    "group": "gy",
    "category": "combination"
  },
  {
    "char": "ぎゅ",
    "romaji": "gyu",
    "group": "gy",
    "category": "combination"
  },
  {
    "char": "ぎょ",
    "romaji": "gyo",
    "group": "gy",
    "category": "combination"
  },
  {
    "char": "じゃ",
    "romaji": "ja",
    "group": "j",
    "category": "combination"
  },
  {
    "char": "じゅ",
    "romaji": "ju",
    "group": "j",
    "category": "combination"
  },
  {
    "char": "じょ",
    "romaji": "jo",
    "group": "j",
    "category": "combination"
  },
  {
    "char": "ぢゃ",
    "romaji": "dya",
    "group": "dy",
    "category": "combination"
  },
  {
    "char": "ぢゅ",
    "romaji": "dyu",
    "group": "dy",
    "category": "combination"
  },
  {
    "char": "ぢょ",
    "romaji": "dyo",
    "group": "dy",
    "category": "combination"
  },
  {
    "char": "びゃ",
    "romaji": "bya",
    "group": "by",
    "category": "combination"
  },
  {
    "char": "びゅ",
    "romaji": "byu",
    "group": "by",
    "category": "combination"
  },
  {
    "char": "びょ",
    "romaji": "byo",
    "group": "by",
    "category": "combination"
  },
  {
    "char": "ぴゃ",
    "romaji": "pya",
    "group": "py",
    "category": "combination"
  },
  {
    "char": "ぴゅ",
    "romaji": "pyu",
    "group": "py",
    "category": "combination"
  },
  {
    "char": "ぴょ",
    "romaji": "pyo",
    "group": "py",
    "category": "combination"
  }
]
